{"cameraMode":{"drawMode":0,"name":"Shaded","section":"Shading Mode"},"sceneLighting":true,"audioPlay":false,"sceneViewState":{"m_AlwaysRefresh":false,"showFog":true,"showSkybox":true,"showFlares":true,"showImageEffects":true,"showParticleSystems":true,"showVisualEffectGraphs":true,"m_FxEnabled":true},"in2DMode":false,"pivot":{"x":1046.47998046875,"y":-10.602237701416016,"z":959.9805297851563},"rotation":{"x":-0.09345921128988266,"y":-0.9007773399353027,"z":0.34866300225257876,"w":-0.24145327508449555},"size":12.297731399536133,"orthographic":false}