{"cameraMode":{"drawMode":0,"name":"Shaded","section":"Shading Mode"},"sceneLighting":false,"audioPlay":false,"sceneViewState":{"m_AlwaysRefresh":false,"showFog":true,"showSkybox":false,"showFlares":true,"showImageEffects":true,"showParticleSystems":true,"showVisualEffectGraphs":true,"m_FxEnabled":true},"in2DMode":false,"pivot":{"x":23.25,"y":5.28000020980835,"z":173.94000244140626},"rotation":{"x":-0.22242824733257295,"y":-0.6505420804023743,"z":0.20784004032611848,"w":-0.6958780884742737},"size":1.7320507764816285,"orthographic":false}